README.md
setup.py
awsornot/__init__.py
awsornot/kv.py
awsornot/kvread.py
awsornot/log.py
awsornot.egg-info/PKG-INFO
awsornot.egg-info/SOURCES.txt
awsornot.egg-info/dependency_links.txt
awsornot.egg-info/requires.txt
awsornot.egg-info/top_level.txt