Metadata-Version: 1.1
Name: awsornot
Version: 1.1.2
Summary: Classes for logging and key/value that work identically whether running on AWS or not
Home-page: https://20ft.nz
Author: David Preece
Author-email: davep@20ft.nz
License: BSD
Keywords: AWS EC2 logging log logger CloudWatch SSM KV Key/Value
Platform: UNKNOWN
Classifier: Development Status :: 5 - Production/Stable
Classifier: Intended Audience :: Developers
Classifier: Intended Audience :: Information Technology
Classifier: Intended Audience :: System Administrators
Classifier: License :: OSI Approved :: BSD License
Classifier: Topic :: System :: Boot
Classifier: Topic :: System :: Boot :: Init
Classifier: Topic :: System :: Clustering
Classifier: Topic :: System :: Distributed Computing
Classifier: Topic :: System :: Software Distribution
Classifier: Topic :: System :: Systems Administration
Classifier: Topic :: Utilities
Classifier: Programming Language :: Python :: 3.4
Classifier: Programming Language :: Python :: 3.5
Classifier: Programming Language :: Python :: 3.6
